paraphernalia/__init__.py
paraphernalia/_project.py
paraphernalia/_random.py
paraphernalia/_settings.py
paraphernalia/colors.py
paraphernalia/glsl.py
paraphernalia/jupyter.py
paraphernalia/review.py
paraphernalia/signature.py
paraphernalia/utils.py
paraphernalia/torch/__init__.py
paraphernalia/torch/clip.py
paraphernalia/torch/dall_e.py
paraphernalia/torch/direct.py
paraphernalia/torch/generator.py
paraphernalia/torch/lightning.py
paraphernalia/torch/modules.py
paraphernalia/torch/noise.py
paraphernalia/torch/siren.py
paraphernalia/torch/taming.py
paraphernalia-0.0.1.dist-info/METADATA
paraphernalia-0.0.1.dist-info/WHEEL
paraphernalia-0.0.1.dist-info/entry_points.txt
paraphernalia-0.0.1.dist-info/licenses/LICENSE
paraphernalia-0.0.1.dist-info/RECORD
